odoo/addons/l10n_it_financial_statements_report/README.rst
odoo/addons/l10n_it_financial_statements_report/__init__.py
odoo/addons/l10n_it_financial_statements_report/__manifest__.py
odoo/addons/l10n_it_financial_statements_report/i18n/it.po
odoo/addons/l10n_it_financial_statements_report/i18n/l10n_it_financial_statements_report.pot
odoo/addons/l10n_it_financial_statements_report/models/__init__.py
odoo/addons/l10n_it_financial_statements_report/models/account_account.py
odoo/addons/l10n_it_financial_statements_report/models/account_group.py
odoo/addons/l10n_it_financial_statements_report/readme/CONTRIBUTORS.md
odoo/addons/l10n_it_financial_statements_report/readme/CREDITS.md
odoo/addons/l10n_it_financial_statements_report/readme/DESCRIPTION.md
odoo/addons/l10n_it_financial_statements_report/readme/INSTALL.md
odoo/addons/l10n_it_financial_statements_report/readme/USAGE.md
odoo/addons/l10n_it_financial_statements_report/report/__init__.py
odoo/addons/l10n_it_financial_statements_report/report/financial_statements_report.py
odoo/addons/l10n_it_financial_statements_report/report/financial_statements_report_xlsx.py
odoo/addons/l10n_it_financial_statements_report/report/reports.xml
odoo/addons/l10n_it_financial_statements_report/report/templates/financial_statements_report.xml
odoo/addons/l10n_it_financial_statements_report/static/description/icon.png
odoo/addons/l10n_it_financial_statements_report/static/description/index.html
odoo/addons/l10n_it_financial_statements_report/tests/__init__.py
odoo/addons/l10n_it_financial_statements_report/tests/test_account.py
odoo/addons/l10n_it_financial_statements_report/tests/test_report.py
odoo/addons/l10n_it_financial_statements_report/wizard/__init__.py
odoo/addons/l10n_it_financial_statements_report/wizard/wizard_financial_statements_report.py
odoo/addons/l10n_it_financial_statements_report/wizard/wizard_financial_statements_report.xml
odoo_addon_l10n_it_financial_statements_report-18.0.1.0.1.dist-info/METADATA
odoo_addon_l10n_it_financial_statements_report-18.0.1.0.1.dist-info/WHEEL
odoo_addon_l10n_it_financial_statements_report-18.0.1.0.1.dist-info/top_level.txt
odoo_addon_l10n_it_financial_statements_report-18.0.1.0.1.dist-info/RECORD
