Metadata-Version: 2.1
Name: odoo-addon-l10n_it_financial_statements_report
Version: 18.0.1.0.1
Requires-Python: >=3.10
Requires-Dist: odoo-addon-account_financial_report==18.0.*
Requires-Dist: odoo-addon-l10n_it_account==18.0.*
Requires-Dist: odoo==18.0.*
Summary: Rendicontazione .pdf e .xls per stato patrimoniale e conto economico a sezioni contrapposte
Home-page: https://github.com/OCA/l10n-italy
License: AGPL-3
Author: Odoo Community Association (OCA), Openforce
Author-email: support@odoo-community.org
Classifier: Programming Language :: Python
Classifier: Framework :: Odoo
Classifier: Framework :: Odoo :: 18.0
Classifier: License :: OSI Approved :: GNU Affero General Public License v3
